groupark/__init__.py
groupark/functional_compounder.py
groupark/sql_compounder.py
groupark-0.2.0.dist-info/LICENSE
groupark-0.2.0.dist-info/WHEEL
groupark-0.2.0.dist-info/METADATA
groupark-0.2.0.dist-info/RECORD
